hotpepper/__init__.py
hotpepper/_utime.cp37-win32.pyd
hotpepper/utime.py
hotpepper-0.0.2.dist-info/LICENSE
hotpepper-0.0.2.dist-info/METADATA
hotpepper-0.0.2.dist-info/WHEEL
hotpepper-0.0.2.dist-info/top_level.txt
hotpepper-0.0.2.dist-info/RECORD
