Metadata-Version: 2.1
Name: hotpepper
Version: 0.0.2
Summary: useful utils
Home-page: https://github.com/3x3x3/hotpepper
Author: 3x3x3
Author-email: ivmivm001@gmail.com
License: MIT
Platform: UNKNOWN
Classifier: License :: OSI Approved :: MIT License
Classifier: Programming Language :: Python :: 3 :: Only
Requires-Python: >=3.6
